setup.py
Sagabuy/__init__.py
Sagabuy/Api/__init__.py
Sagabuy/Api/giftcard.py
Sagabuy/Config/__init__.py
Sagabuy/Config/config.py
Sagabuy/Oauth/__init__.py
Sagabuy/Oauth/oauth.py
sagabuy_giftcard_python_sdk.egg-info/PKG-INFO
sagabuy_giftcard_python_sdk.egg-info/SOURCES.txt
sagabuy_giftcard_python_sdk.egg-info/dependency_links.txt
sagabuy_giftcard_python_sdk.egg-info/top_level.txt