Metadata-Version: 1.0
Name: sagabuy-giftcard-python-sdk
Version: 1.0.0
Summary: sagabuy giftcard python sdk
Home-page: UNKNOWN
Author: 王津津
Author-email: wangjinjin@huanyuzhike.com
License: MIT Licence
Keywords: python,openapi
Platform: UNKNOWN
